math_core/__init__.py
math_core/_math_core_rust.cpython-313-i386-linux-musl.so
math_core/_math_core_rust.pyi
math_core/py.typed
math_core-0.2.2.dist-info/METADATA
math_core-0.2.2.dist-info/WHEEL
math_core-0.2.2.dist-info/licenses/LICENSE
math_core.libs/libgcc_s-f5fcfe20.so.1
math_core-0.2.2.dist-info/RECORD
