Metadata-Version: 2.4
Name: math-core
Version: 0.2.2
Classifier: Programming Language :: Rust
Classifier: Programming Language :: Python :: Implementation :: CPython
Classifier: License :: OSI Approved :: MIT License
Requires-Dist: pytest ; extra == 'tests'
Provides-Extra: tests
License-File: LICENSE
Summary: Convert LaTeX math to MathML Core
Author-email: Thomas MK <tmke8@posteo.net>
License-Expression: MIT
Requires-Python: >=3.10
Project-URL: repository, https://github.com/tmke8/math-core.git
